neverbounce/__init__.py
neverbounce/client.py
neverbounce/exceptions.py
neverbounce/objects.py
neverbounce-0.2.0.dist-info/DESCRIPTION.rst
neverbounce-0.2.0.dist-info/METADATA
neverbounce-0.2.0.dist-info/RECORD
neverbounce-0.2.0.dist-info/WHEEL
neverbounce-0.2.0.dist-info/metadata.json
neverbounce-0.2.0.dist-info/top_level.txt
