Metadata-Version: 2.0
Name: neverbounce
Version: 0.2.0
Summary: API library for the NeverBounce email verification service.
Home-page: https://github.com/martinkosir/neverbounce-python
Author: Martin Kosír
Author-email: martin@martinkosir.net
License: MIT
Keywords: api,email,verification
Platform: UNKNOWN
Classifier: Development Status :: 3 - Alpha
Classifier: Intended Audience :: Developers
Classifier: Topic :: Communications :: Email
Classifier: License :: OSI Approved :: MIT License
Classifier: Programming Language :: Python
Classifier: Programming Language :: Python :: 2
Classifier: Programming Language :: Python :: 2.7
Classifier: Programming Language :: Python :: 3
Classifier: Programming Language :: Python :: 3.3
Classifier: Programming Language :: Python :: 3.4
Classifier: Programming Language :: Python :: 3.5
Requires-Dist: requests (>=2.9.0)
